ConfigIniGUI/__init__.py
ConfigIniGUI/example.py
ConfigIniGUI-0.0.1.dist-info/LICENSE
ConfigIniGUI-0.0.1.dist-info/METADATA
ConfigIniGUI-0.0.1.dist-info/WHEEL
ConfigIniGUI-0.0.1.dist-info/top_level.txt
ConfigIniGUI-0.0.1.dist-info/RECORD
