Metadata-Version: 2.1
Name: ConfigIniGUI
Version: 0.0.1
Summary: A Python Web GUI for any projects Config Ini File.
Home-page: https://github.com/Michu44/PythonConfigIniGUI
Author: Michael Lopez
Author-email: author@example.com
Classifier: Programming Language :: Python :: 3
Classifier: License :: OSI Approved :: MIT License
Classifier: Operating System :: OS Independent
License-File: LICENSE
